Aoipy/AoiErrorHandling.py
Aoipy/__init__.py
Aoipy/all_Functions.txt
Aoipy/all_functions.py
Aoipy/tools.py
Aoipy/Classes/AoiPyClient.py
Aoipy/Classes/Cogs.py
Aoipy/Classes/CommandHandler.py
Aoipy/Classes/Commands.py
Aoipy/Classes/Events.py
Aoipy/Classes/__init__.py
Aoipy/Function/AoiCore.py
Aoipy/Function/__init__.py
Aoipy/Function/Guilds/Channels.py
Aoipy/Function/Guilds/__init__.py
Aoipy/Function/Users/__init__.py
Aoipy/Function/Users/funcs.py
Aoipy/Functions/AoiCore.py
Aoipy/Functions/__init__.py
Aoipy/Functions/clientActivity.py
Aoipy/Functions/Channels/__init__.py
Aoipy/Functions/Channels/channelCategoryID.py
Aoipy/Functions/Channels/channelCategoryName.py
Aoipy/Functions/Channels/channelChangedRoles.py
Aoipy/Functions/Channels/channelCreated.py
Aoipy/Functions/Channels/channelDelay.py
Aoipy/Functions/Channels/channelID.py
Aoipy/Functions/Channels/channelMention.py
Aoipy/Functions/Channels/channelName.py
Aoipy/Functions/Channels/channelNsfw.py
Aoipy/Functions/Channels/channelPosition.py
Aoipy/Functions/Channels/channelType.py
Aoipy/Functions/Channels/channelURL.py
Aoipy/Functions/Channels/threadAutoArchive.py
Aoipy/Functions/Client/__init__.py
Aoipy/Functions/Client/ping.py
Aoipy/Functions/Events/__init__.py
Aoipy/Functions/Events/deletedChannel.py
Aoipy/Functions/Events/newChannel.py
Aoipy/Functions/Events/oldChannel.py
Aoipy/Functions/Guilds/Channels.py
Aoipy/Functions/Guilds/__init__.py
Aoipy/Functions/Guilds/channelDelay.py
Aoipy/Functions/Guilds/channelID.py
Aoipy/Functions/Guilds/channelMention.py
Aoipy/Functions/Guilds/channelName.py
Aoipy/Functions/Guilds/currentChannelID.py
Aoipy/Functions/Guilds/currentGuildID.py
Aoipy/Functions/Guilds/guild.py
Aoipy/Functions/Guilds/guildID.py
Aoipy/Functions/Guilds/guildName.py
Aoipy/Functions/Guilds/guildTextChannels.py
Aoipy/Functions/Messages/__init__.py
Aoipy/Functions/Messages/sendEmbed.py
Aoipy/Functions/Messages/sendMessage.py
Aoipy/Functions/Python/__init__.py
Aoipy/Functions/Python/count.py
Aoipy-0.15.0.dist-info/LICENSE
Aoipy-0.15.0.dist-info/METADATA
Aoipy-0.15.0.dist-info/WHEEL
Aoipy-0.15.0.dist-info/top_level.txt
Aoipy-0.15.0.dist-info/RECORD
